Monociclo/RegisterUnit/ru.sv
module RegisterUnit(
    input logic [4:0] readRegister1,              // Registro fuente 1
    input logic [4:0] readRegister2,              // Registro fuente 2
    output logic [31:0] dataOut1,                 // Datos leídos del registro fuente 1
    output logic [31:0] dataOut2,                 // Datos leídos del registro fuente 2
    input logic [4:0] writeRegister,              // Registro de destino para escritura
    input logic writeEnable,                      // Habilitador de escritura, señal desde ControlUnit
    input logic [31:0] dataIn,                    // Datos a escribir
    input logic clk                               // Señal de reloj
);

    parameter MAX_REGISTERS = 32;                  // Número máximo de registros
    parameter BITS_PER_REGISTER = 32;               // Bits por registro

    logic [BITS_PER_REGISTER-1:0] registers [0:MAX_REGISTERS-1]; // Array de registros

    // Inicialización de registros
    initial begin
        for (int i = 0; i < MAX_REGISTERS; i = i + 1) begin
            registers[i] = 32'h0;                   // Inicializa todos los registros a 0
        end
        registers[2] = 32'd1024;                     // Inicializa el registro 2 con el valor 1024
    end

    // Proceso de escritura en el registro
    always @(posedge clk) begin
        // Verifica si se debe escribir y que el registro de destino no sea el registro 0
        if (writeEnable && writeRegister !== 5'b00000) begin
            registers[writeRegister] = dataIn;      // Escribe en el registro de destino
        end
    end

    // Asignaciones para lectura de registros
    assign dataOut1 = registers[readRegister1];    // Asigna el dato del registro fuente 1
    assign dataOut2 = registers[readRegister2];    // Asigna el dato del registro fuente 2

endmodule

Monociclo/RegisterUnit/testRu.sv
`timescale 1ns/1ps

module RegisterUnit_tb;

    // Señales de entrada y salida
    reg [4:0] readRegister1;                // Registro fuente 1 para lectura
    reg [4:0] readRegister2;                // Registro fuente 2 para lectura
    reg [4:0] writeRegister;                // Registro de destino para escritura
    reg writeEnable;                        // Señal que habilita la escritura
    reg [31:0] dataIn;                      // Datos a escribir en el registro
    reg clk;                                 // Señal de reloj
    wire [31:0] dataOut1;                  // Datos leídos del registro fuente 1
    wire [31:0] dataOut2;                  // Datos leídos del registro fuente 2

    // Instancia del módulo RegisterUnit
    RegisterUnit uut (
        .readRegister1(readRegister1),
        .readRegister2(readRegister2),
        .dataOut1(dataOut1),
        .dataOut2(dataOut2),
        .writeRegister(writeRegister),
        .writeEnable(writeEnable),
        .dataIn(dataIn),
        .clk(clk)
    );

    // Generador de reloj
    initial begin
        clk = 0;                             // Inicializa el reloj en 0
        forever #5 clk = ~clk;               // Genera un reloj alternando cada 5 ns (periodo de 10 ns)
    end

    // Proceso de simulación
    initial begin
        // Inicializa las señales
        writeEnable = 0;                    // Deshabilita la escritura al inicio
        writeRegister = 5'd0;                // Registro de escritura inicializado en 0
        dataIn = 32'd0;                      // Datos de entrada inicializados en 0
        readRegister1 = 5'd0;                // Registro fuente 1 inicializado en 0
        readRegister2 = 5'd0;                // Registro fuente 2 inicializado en 0

        // Espera a que los registros se inicialicen
        #10;

        // Verificar la inicialización de los registros
        readRegister1 = 5'd2;                // Configura para leer el registro 2
        #5;                                   // Espera un ciclo de reloj
        $display("Lectura inicial | Registro 2: %d (esperado: 1024)", dataOut1); // Muestra el valor del registro 2

        // Escritura en el registro 3
        writeEnable = 1;                     // Habilita la escritura
        writeRegister = 5'd3;                // Configura el registro 3 como destino
        dataIn = 32'd123;                    // Datos a escribir
        #10;                                  // Espera para permitir la escritura
        writeEnable = 0;                     // Deshabilita la escritura

        // Lectura del registro 3 para verificar la escritura
        readRegister1 = 5'd3;                // Configura para leer el registro 3
        #5;                                   // Espera un ciclo de reloj
        $display("Lectura | Registro 3: %d (esperado: 123)", dataOut1); // Muestra el valor del registro 3

        // Escritura en el registro 4
        writeEnable = 1;                     // Habilita la escritura
        writeRegister = 5'd4;                // Configura el registro 4 como destino
        dataIn = 32'd456;                    // Datos a escribir
        #10;                                  // Espera para permitir la escritura
        writeEnable = 0;                     // Deshabilita la escritura

        // Lectura de los registros 3 y 4
        readRegister1 = 5'd3;                // Configura para leer el registro 3
        readRegister2 = 5'd4;                // Configura para leer el registro 4
        #5;                                   // Espera un ciclo de reloj
        $display("Lectura | Registro 3: %d (esperado: 123)", dataOut1); // Muestra el valor del registro 3
        $display("Lectura | Registro 4: %d (esperado: 456)", dataOut2); // Muestra el valor del registro 4

        // Intento de escritura en el registro 0 (debe ser ignorado)
        writeEnable = 1;                     // Habilita la escritura
        writeRegister = 5'd0;                // Configura el registro 0 como destino
        dataIn = 32'd999;                    // Datos a escribir
        #10;                                  // Espera para permitir la escritura
        writeEnable = 0;                     // Deshabilita la escritura

        // Verificar que el registro 0 sigue en 0
        readRegister1 = 5'd0;                // Configura para leer el registro 0
        #5;                                   // Espera un ciclo de reloj
        $display("Lectura | Registro 0: %d (esperado: 0)", dataOut1); // Muestra el valor del registro 0

        // Fin de la simulación
        $finish;
    end

    // Guardado de señales en un archivo VCD para visualización
    initial begin
        $dumpfile("RegisterUnit_tb.vcd");     // Define el archivo de salida para las señales
        $dumpvars(0, RegisterUnit_tb);        // Guarda todas las variables del testbench
    end

endmodule

Monociclo/RegisterUnit/RegisterUnit_tb.vcd
$date
	Thu Oct 31 01:47:49 2024
$end
$version
	Icarus Verilog
$end
$timescale
	1ps
$end
$scope module RegisterUnit_tb $end
$var wire 32 ! dataOut2 [31:0] $end
$var wire 32 " dataOut1 [31:0] $end
$var reg 1 # clk $end
$var reg 32 $ dataIn [31:0] $end
$var reg 5 % readRegister1 [4:0] $end
$var reg 5 & readRegister2 [4:0] $end
$var reg 1 ' writeEnable $end
$var reg 5 ( writeRegister [4:0] $end
$scope module uut $end
$var wire 1 # clk $end
$var wire 32 ) dataIn [31:0] $end
$var wire 32 * dataOut1 [31:0] $end
$var wire 32 + dataOut2 [31:0] $end
$var wire 5 , readRegister1 [4:0] $end
$var wire 5 - readRegister2 [4:0] $end
$var wire 1 ' writeEnable $end
$var wire 5 . writeRegister [4:0] $end
$var parameter 32 / BITS_PER_REGISTER $end
$var parameter 32 0 MAX_REGISTERS $end
$scope begin $ivl_for_loop0 $end
$var integer 32 1 i [31:0] $end
$upscope $end
$upscope $end
$upscope $end
$enddefinitions $end
$comment Show the parameter values. $end
$dumpall
b100000 0
b100000 /
$end
#0
$dumpvars
b100000 1
b0 .
b0 -
b0 ,
b0 +
b0 *
b0 )
b0 (
0'
b0 &
b0 %
b0 $
0#
b0 "
b0 !
$end
#5000
1#
#10000
0#
b10000000000 "
b10000000000 *
b10 %
b10 ,
#15000
1#
b1111011 $
b1111011 )
b11 (
b11 .
1'
#20000
0#
#25000
1#
b1111011 "
b1111011 *
b11 %
b11 ,
0'
#30000
0#
b111001000 $
b111001000 )
b100 (
b100 .
1'
#35000
1#
#40000
0#
b111001000 !
b111001000 +
b100 &
b100 -
0'
#45000
1#
b1111100111 $
b1111100111 )
b0 (
b0 .
1'
#50000
0#
#55000
1#
b0 "
b0 *
b0 %
b0 ,
0'
