Monociclo/BranchUnit/branchU.sv
module BranchUnit(
    input logic [31:0] regValue1,            // Valor del registro 1 (rs1)
    input logic [31:0] regValue2,            // Valor del registro 2 (rs2)
    input logic [4:0] branchOperation,       // Operación de salto (BrOp)
    
    output logic nextPCSource                // Señal de destino para el siguiente PC
);

    // Lógica combinacional para determinar el siguiente destino del PC
    always @(*) begin
        // Si se activa la señal de salto incondicional
        if (branchOperation[4] == 1'b1) begin
            nextPCSource = 1'b1;               // Salto incondicional
        end else begin
            // Si no hay operación de salto
            if (branchOperation[4:3] == 2'b0) begin
                nextPCSource = 1'b0;           // No se realiza salto
            end else begin
                // Determina el tipo de comparación para el salto
                case (branchOperation)
                    5'b01000: nextPCSource = (regValue1 == regValue2);  // Igualdad
                    5'b01001: nextPCSource = (regValue1 != regValue2);  // Desigualdad
                    5'b01100: nextPCSource = ($signed(regValue1) < $signed(regValue2)); // Menor (signed)
                    5'b01101: nextPCSource = ($signed(regValue1) >= $signed(regValue2)); // Mayor o igual (signed)
                    5'b01110: nextPCSource = (regValue1 < regValue2);  // Menor (unsigned)
                    5'b01111: nextPCSource = (regValue1 >= regValue2); // Mayor o igual (unsigned)
                    default: nextPCSource = 0;  // Valor por defecto (no salto)
                endcase
            end
        end
    end

endmodule

Monociclo/BranchUnit/testBU.sv
`timescale 1ns/1ps

module BranchUnit_tb;

    // Señales de entrada
    reg [31:0] regValue1;            // Valor del registro 1 (rs1)
    reg [31:0] regValue2;            // Valor del registro 2 (rs2)
    reg [4:0] branchOperation;       // Operación de salto (BrOp)

    // Señal de salida
    wire nextPCSource;               // Señal de destino para el siguiente PC

    // Instancia del módulo BranchUnit
    BranchUnit uut (
        .regValue1(regValue1),
        .regValue2(regValue2),
        .branchOperation(branchOperation),
        .nextPCSource(nextPCSource)
    );

    // Proceso de simulación
    initial begin
        // Inicializa las señales
        regValue1 = 32'd0;             // Inicializa regValue1 a 0
        regValue2 = 32'd0;             // Inicializa regValue2 a 0
        branchOperation = 5'b00000;    // Inicializa branchOperation a 0

        // Espera un poco antes de comenzar las pruebas
        #10;

        // Prueba de salto incondicional
        branchOperation = 5'b10000;    // Salto incondicional
        #10;
        $display("Salto incondicional | nextPCSource: %b (esperado: 1)", nextPCSource);

        // Prueba de igualdad
        regValue1 = 32'd10;
        regValue2 = 32'd10;
        branchOperation = 5'b01000;    // Comparación de igualdad
        #10;
        $display("Igualdad | nextPCSource: %b (esperado: 1)", nextPCSource);

        // Prueba de desigualdad
        regValue1 = 32'd10;
        regValue2 = 32'd20;
        branchOperation = 5'b01001;    // Comparación de desigualdad
        #10;
        $display("Desigualdad | nextPCSource: %b (esperado: 0)", nextPCSource);

        // Prueba de menor (signed)
        regValue1 = 32'd10;
        regValue2 = 32'd20;
        branchOperation = 5'b01100;    // Comparación menor (signed)
        #10;
        $display("Menor (signed) | nextPCSource: %b (esperado: 1)", nextPCSource);

        // Prueba de mayor o igual (signed)
        regValue1 = 32'd20;
        regValue2 = 32'd10;
        branchOperation = 5'b01101;    // Comparación mayor o igual (signed)
        #10;
        $display("Mayor o igual (signed) | nextPCSource: %b (esperado: 1)", nextPCSource);

        // Prueba de menor (unsigned)
        regValue1 = 32'd10;
        regValue2 = 32'd20;
        branchOperation = 5'b01110;    // Comparación menor (unsigned)
        #10;
        $display("Menor (unsigned) | nextPCSource: %b (esperado: 1)", nextPCSource);

        // Prueba de mayor o igual (unsigned)
        regValue1 = 32'd20;
        regValue2 = 32'd10;
        branchOperation = 5'b01111;    // Comparación mayor o igual (unsigned)
        #10;
        $display("Mayor o igual (unsigned) | nextPCSource: %b (esperado: 1)", nextPCSource);

        // Fin de la simulación
        $finish;
    end

    // Guardado de señales en un archivo VCD para visualización
    initial begin
        $dumpfile("BranchUnit_tb.vcd");  // Archivo de salida para la simulación
        $dumpvars(0, BranchUnit_tb);      // Registra todas las variables en el testbench
    end

endmodule

Monociclo/BranchUnit/BranchUnit_tb.vcd
$date
	Thu Oct 31 02:21:14 2024
$end
$version
	Icarus Verilog
$end
$timescale
	1ps
$end
$scope module BranchUnit_tb $end
$var wire 1 ! nextPCSource $end
$var reg 5 " branchOperation [4:0] $end
$var reg 32 # regValue1 [31:0] $end
$var reg 32 $ regValue2 [31:0] $end
$scope module uut $end
$var wire 5 % branchOperation [4:0] $end
$var wire 32 & regValue1 [31:0] $end
$var wire 32 ' regValue2 [31:0] $end
$var reg 1 ! nextPCSource $end
$upscope $end
$upscope $end
$enddefinitions $end
$comment Show the parameter values. $end
$dumpall
$end
#0
$dumpvars
b0 '
b0 &
b0 %
b0 $
b0 #
b0 "
0!
$end
#10000
1!
b10000 "
b10000 %
#20000
b1000 "
b1000 %
b1010 $
b1010 '
b1010 #
b1010 &
#30000
b1001 "
b1001 %
b10100 $
b10100 '
#40000
b1100 "
b1100 %
#50000
b1101 "
b1101 %
b1010 $
b1010 '
b10100 #
b10100 &
#60000
b1110 "
b1110 %
b10100 $
b10100 '
b1010 #
b1010 &
#70000
b1111 "
b1111 %
b1010 $
b1010 '
b10100 #
b10100 &
