Monociclo/PC/pc.sv
module PC(address, clk, newAddress);

    parameter NEWADDRESSLENGTH = 32;
    parameter MAXBITSPERREGISTER = 32;

    input logic [NEWADDRESSLENGTH-1:0] address;
    input logic clk;

    output logic [NEWADDRESSLENGTH-1:0] newAddress;

    initial begin
        newAddress = 32'b0;
    end

    always @(posedge clk) begin
        newAddress = address;
    end  
endmodule;

Monociclo/PC/testPC.sv
`timescale 1ns/1ps

module PC_tb;

    parameter NEWADDRESSLENGTH = 32;
    parameter MAXBITSPERREGISTER = 32;

    // Señales de entrada y salida
    reg [NEWADDRESSLENGTH-1:0] address;
    reg clk;
    wire [NEWADDRESSLENGTH-1:0] newAddress;

    // Instancia del módulo PC
    PC uut (
        .address(address),
        .clk(clk),
        .newAddress(newAddress)
    );

    // Generación de señal de reloj
    initial begin
        clk = 0;
        forever #5 clk = ~clk;  // Reloj con periodo de 10 ns
    end

    // Proceso de simulación
    initial begin
        // Inicialización de las entradas
        address = 32'h00000000;

        // Aplicación de estímulos
        #10 address = 32'h00000004;
        #10 address = 32'h00000008;
        #10 address = 32'h0000000C;
        #10 address = 32'h00000010;
        
        // Fin de la simulación
        #10 $finish;
    end

    // Guardar el archivo de señal VCD para visualizar en WaveTrace
    initial begin
        $dumpfile("PC_tb.vcd");
        $dumpvars(0, PC_tb);
    end

endmodule

Monociclo/PC/PC_tb.vcd
$date
	Thu Oct 31 00:07:22 2024
$end
$version
	Icarus Verilog
$end
$timescale
	1ps
$end
$scope module PC_tb $end
$var wire 32 ! newAddress [31:0] $end
$var parameter 32 " MAXBITSPERREGISTER $end
$var parameter 32 # NEWADDRESSLENGTH $end
$var reg 32 $ address [31:0] $end
$var reg 1 % clk $end
$scope module uut $end
$var wire 32 & address [31:0] $end
$var wire 1 % clk $end
$var parameter 32 ' MAXBITSPERREGISTER $end
$var parameter 32 ( NEWADDRESSLENGTH $end
$var reg 32 ) newAddress [31:0] $end
$upscope $end
$upscope $end
$enddefinitions $end
$comment Show the parameter values. $end
$dumpall
b100000 (
b100000 '
b100000 #
b100000 "
$end
#0
$dumpvars
b0 )
b0 &
0%
b0 $
b0 !
$end
#5000
1%
#10000
0%
b100 $
b100 &
#15000
b100 !
b100 )
1%
#20000
0%
b1000 $
b1000 &
#25000
b1000 !
b1000 )
1%
#30000
0%
b1100 $
b1100 &
#35000
b1100 !
b1100 )
1%
#40000
0%
b10000 $
b10000 &
#45000
b10000 !
b10000 )
1%
