Monociclo/ALU/alu.sv
module ArithmeticLogicUnit (
    input  logic [31:0] operandA,     // First input operand
    input  logic [31:0] operandB,     // Second input operand
    input  logic [3:0]  operation,    // Operation selector
    output logic [31:0] result        // Operation result
);

    // Combinational logic block for ALU operations
    always_comb begin
        case(operation)
            // Arithmetic Operations
            4'b0000: result = operandA + operandB;                    // Addition
            4'b1000: result = operandA - operandB;                    // Subtraction
            
            // Logical Operations
            4'b0111: result = operandA & operandB;                    // Bitwise AND
            4'b0110: result = operandA | operandB;                    // Bitwise OR
            4'b0100: result = operandA ^ operandB;                    // Bitwise XOR
            
            // Shift Operations
            4'b0001: result = operandA << operandB;                   // Logical left shift
            4'b0101: result = operandA >> operandB;                   // Logical right shift (fixed from 0105)
            4'b1101: result = operandA >>> operandB;                  // Arithmetic right shift
            4'b0010: result = $signed(operandA) << $signed(operandB); // Arithmetic left shift
            
            // Comparison Operations
            4'b0011: result = ($signed(operandA) < $signed(operandB)) ? 32'h1 : 32'h0; // Signed comparison
            
            // Default case
            default: result = operandA;                               // Pass through operandA
        endcase
    end

endmodule

Monociclo/ALU/testAlu.sv
module ALU_testbench();
    // Signal declarations
    logic [31:0] operandA;
    logic [31:0] operandB;
    logic [3:0]  operation;
    logic [31:0] result;
    
    // Instantiate the ALU
    ArithmeticLogicUnit dut(
        .operandA(operandA),
        .operandB(operandB),
        .operation(operation),
        .result(result)
    );
    
    // Test stimulus
    initial begin
        // Test 1: Addition
        operandA = 32'h5; operandB = 32'h3; operation = 4'b0000;
        #10;
        if (result !== 32'h8) $display("Addition failed");
        
        // Test 2: Subtraction
        operandA = 32'h5; operandB = 32'h3; operation = 4'b1000;
        #10;
        if (result !== 32'h2) $display("Subtraction failed");
        
        // Test 3: Bitwise AND
        operandA = 32'hF0F0; operandB = 32'hFF00; operation = 4'b0111;
        #10;
        if (result !== 32'hF000) $display("AND failed");
        
        // Test 4: Bitwise OR
        operandA = 32'hF0F0; operandB = 32'h0F0F; operation = 4'b0110;
        #10;
        if (result !== 32'hFFFF) $display("OR failed");
        
        // Test 5: Bitwise XOR
        operandA = 32'hFFFF; operandB = 32'hF0F0; operation = 4'b0100;
        #10;
        if (result !== 32'h0F0F) $display("XOR failed");
        
        // Test 6: Logical left shift
        operandA = 32'h1; operandB = 32'h2; operation = 4'b0001;
        #10;
        if (result !== 32'h4) $display("Left shift failed");
        
        // Test 7: Logical right shift
        operandA = 32'h8; operandB = 32'h1; operation = 4'b0101;
        #10;
        if (result !== 32'h4) $display("Right shift failed");
        
        // Test 8: Arithmetic right shift
        operandA = 32'h80000000; operandB = 32'h1; operation = 4'b1101;
        #10;
        if (result !== 32'hC0000000) $display("Arithmetic right shift failed");
        
        // Test 9: Arithmetic left shift
        operandA = 32'h1; operandB = 32'h2; operation = 4'b0010;
        #10;
        if (result !== 32'h4) $display("Arithmetic left shift failed");
        
        // Test 10: Signed comparison
        operandA = 32'hFFFFFFFF; operandB = 32'h1; operation = 4'b0011;
        #10;
        if (result !== 32'h1) $display("Signed comparison failed");
        
        // Test 11: Default case
        operandA = 32'h5; operandB = 32'h3; operation = 4'b1111;
        #10;
        if (result !== operandA) $display("Default case failed");
        
        $display("All tests completed!");
        $finish;
    end
    
    // Waveform generation
    initial begin
        $dumpfile("alu_test.vcd");
        $dumpvars(0, ALU_testbench);
    end

endmodule

Monociclo/ALU/alu_test.vcd
$date
	Mon Nov 04 21:11:13 2024
$end
$version
	Icarus Verilog
$end
$timescale
	1s
$end
$scope module ALU_testbench $end
$var wire 32 ! result [31:0] $end
$var reg 32 " operandA [31:0] $end
$var reg 32 # operandB [31:0] $end
$var reg 4 $ operation [3:0] $end
$scope module dut $end
$var wire 32 % operandA [31:0] $end
$var wire 32 & operandB [31:0] $end
$var wire 4 ' operation [3:0] $end
$var reg 32 ( result [31:0] $end
$upscope $end
$upscope $end
$enddefinitions $end
$comment Show the parameter values. $end
$dumpall
$end
#0
$dumpvars
b1000 (
b0 '
b11 &
b101 %
b0 $
b11 #
b101 "
b1000 !
$end
#10
b10 !
b10 (
b1000 $
b1000 '
#20
b1111000000000000 !
b1111000000000000 (
b111 $
b111 '
b1111111100000000 #
b1111111100000000 &
b1111000011110000 "
b1111000011110000 %
#30
b1111111111111111 !
b1111111111111111 (
b110 $
b110 '
b111100001111 #
b111100001111 &
#40
b111100001111 !
b111100001111 (
b100 $
b100 '
b1111000011110000 #
b1111000011110000 &
b1111111111111111 "
b1111111111111111 %
#50
b100 !
b100 (
b1 $
b1 '
b10 #
b10 &
b1 "
b1 %
#60
b101 $
b101 '
b1 #
b1 &
b1000 "
b1000 %
#70
b1000000000000000000000000000000 !
b1000000000000000000000000000000 (
b1101 $
b1101 '
b10000000000000000000000000000000 "
b10000000000000000000000000000000 %
#80
b100 !
b100 (
b10 $
b10 '
b10 #
b10 &
b1 "
b1 %
#90
b1 !
b1 (
b11 $
b11 '
b1 #
b1 &
b11111111111111111111111111111111 "
b11111111111111111111111111111111 %
#100
b101 !
b101 (
b1111 $
b1111 '
b11 #
b11 &
b101 "
b101 %
